brainfreeze
