Metadata-Version: 1.0
Name: BrainFreeze
Version: 0.1rc1
Summary: 
